[{"key": -1, "bias": 0, "activation": "", "type": "input"}, {"key": -2, "bias": 0, "activation": "", "type": "input"}, {"key": -3, "bias": 0, "activation": "", "type": "input"}, {"key": -4, "bias": 0, "activation": "", "type": "input"}, {"key": -5, "bias": 0, "activation": "", "type": "input"}, {"key": -6, "bias": 0, "activation": "", "type": "input"}, {"key": -7, "bias": 0, "activation": "", "type": "input"}, {"key": -8, "bias": 0, "activation": "", "type": "input"}, {"key": -9, "bias": 0, "activation": "", "type": "input"}, {"key": -10, "bias": 0, "activation": "", "type": "input"}, {"key": -11, "bias": 0, "activation": "", "type": "input"}, {"key": -12, "bias": 0, "activation": "", "type": "input"}, {"key": -13, "bias": 0, "activation": "", "type": "input"}, {"key": -14, "bias": 0, "activation": "", "type": "input"}, {"key": -15, "bias": 0, "activation": "", "type": "input"}, {"key": -16, "bias": 0, "activation": "", "type": "input"}, {"key": -17, "bias": 0, "activation": "", "type": "input"}, {"key": -18, "bias": 0, "activation": "", "type": "input"}, {"key": -19, "bias": 0, "activation": "", "type": "input"}, {"key": -20, "bias": 0, "activation": "", "type": "input"}, {"key": -21, "bias": 0, "activation": "", "type": "input"}, {"key": -22, "bias": 0, "activation": "", "type": "input"}, {"key": 687949, "bias": 0.2749658010116817, "activation": "relu", "type": "hidden"}, {"key": 706174, "bias": 0.025535539295999388, "activation": "relu", "type": "hidden"}, {"key": 722505, "bias": 0.44557653153979565, "activation": "relu", "type": "hidden"}, {"key": 723054, "bias": 0.14607838326418607, "activation": "relu", "type": "hidden"}, {"key": 723874, "bias": -1.6037573781262324, "activation": "relu", "type": "hidden"}, {"key": 733740, "bias": 0.10611644019795616, "activation": "relu", "type": "hidden"}, {"key": 766870, "bias": -1.3116682634190302, "activation": "relu", "type": "hidden"}, {"key": 942029, "bias": -0.3179615588719469, "activation": "relu", "type": "hidden"}, {"key": 1799367, "bias": -0.06834175437349613, "activation": "relu", "type": "hidden"}, {"key": 0, "bias": 1.085725639095576, "activation": "relu", "type": "output"}, {"key": 1, "bias": 0.12461693980476168, "activation": "relu", "type": "output"}]